prediction_markets/__init__.py
prediction_markets/market.py
prediction_markets/markets/kalshi.py
prediction_markets/markets/polymarket.py
prediction_markets.py-0.1.dist-info/LICENSE
prediction_markets.py-0.1.dist-info/METADATA
prediction_markets.py-0.1.dist-info/WHEEL
prediction_markets.py-0.1.dist-info/top_level.txt
prediction_markets.py-0.1.dist-info/RECORD
