Metadata-Version: 2.2
Name: prediction-markets.py
Version: 0.1
Summary: Wraps multiple prediction market's API into one lightweight & simple Python interface
Author-email: Peter Zhou <peterzhou561@gmail.com>
Project-URL: Homepage, https://github.com/GodlyPeeta/python-prediction-markets
Project-URL: Issues, https://github.com/GodlyPeeta/python-prediction-markets/issues
License-File: LICENSE
